[{"timestamp":"2024-12-04T18:54:43.385Z","count":0,"uniques":0},{"timestamp":"2024-12-05T18:54:43.385Z","count":0,"uniques":0},{"timestamp":"2024-12-06T18:54:43.385Z","count":0,"uniques":0},{"timestamp":"2024-12-07T18:54:43.385Z","count":0,"uniques":0},{"timestamp":"2024-12-08T18:54:43.385Z","count":0,"uniques":0},{"timestamp":"2024-12-09T18:54:43.385Z","count":0,"uniques":0},{"timestamp":"2024-12-10T18:54:43.385Z","count":0,"uniques":0},{"timestamp":"2024-12-11T18:54:43.385Z","count":0,"uniques":0},{"timestamp":"2024-12-12T18:54:43.385Z","count":0,"uniques":0},{"timestamp":"2024-12-13T18:54:43.385Z","count":0,"uniques":0},{"timestamp":"2024-12-14T18:54:43.385Z","count":0,"uniques":0},{"timestamp":"2024-12-15T18:54:43.385Z","count":0,"uniques":0},{"timestamp":"2024-12-16T18:54:43.385Z","count":0,"uniques":0},{"timestamp":"2024-12-17T18:54:43.385Z","count":0,"uniques":0},{"timestamp":"2024-12-18T18:54:43.385Z","count":0,"uniques":0},{"timestamp":"2024-12-19T18:54:43.385Z","count":0,"uniques":0},{"timestamp":"2024-12-20T18:54:43.385Z","count":0,"uniques":0},{"timestamp":"2024-12-21T18:54:43.385Z","count":0,"uniques":0},{"timestamp":"2024-12-22T18:54:43.385Z","count":0,"uniques":0},{"timestamp":"2024-12-23T18:54:43.385Z","count":0,"uniques":0},{"timestamp":"2024-12-24T18:54:43.385Z","count":0,"uniques":0},{"timestamp":"2024-12-25T18:54:43.385Z","count":0,"uniques":0},{"timestamp":"2024-12-26T18:54:43.385Z","count":0,"uniques":0},{"timestamp":"2024-12-27T18:54:43.385Z","count":0,"uniques":0},{"timestamp":"2024-12-28T18:54:43.385Z","count":0,"uniques":0},{"timestamp":"2024-12-29T18:54:43.385Z","count":0,"uniques":0},{"timestamp":"2024-12-30T18:54:43.385Z","count":0,"uniques":0},{"timestamp":"2024-12-31T18:54:43.385Z","count":0,"uniques":0},{"timestamp":"2025-01-01T18:54:43.385Z","count":0,"uniques":0},{"timestamp":"2025-01-02T18:54:43.385Z","count":0,"uniques":0},{"timestamp":"2025-01-03T18:54:43.385Z","count":0,"uniques":0},{"timestamp":"2025-01-04T18:54:43.385Z","count":0,"uniques":0},{"timestamp":"2025-01-05T18:54:43.385Z","count":0,"uniques":0},{"timestamp":"2025-01-06T18:54:43.385Z","count":0,"uniques":0},{"timestamp":"2025-01-07T18:54:43.385Z","count":0,"uniques":0},{"timestamp":"2025-01-08T18:54:43.385Z","count":0,"uniques":0},{"timestamp":"2025-01-09T18:54:43.385Z","count":0,"uniques":0},{"timestamp":"2025-01-10T18:54:43.385Z","count":0,"uniques":0},{"timestamp":"2025-01-11T18:54:43.385Z","count":0,"uniques":0},{"timestamp":"2025-01-12T18:54:43.385Z","count":0,"uniques":0},{"timestamp":"2025-01-13T18:54:43.385Z","count":0,"uniques":0},{"timestamp":"2025-01-14T18:54:43.385Z","count":0,"uniques":0},{"timestamp":"2025-01-15T18:54:43.385Z","count":0,"uniques":0},{"timestamp":"2025-01-16T18:54:43.385Z","count":0,"uniques":0},{"timestamp":"2025-01-17T18:54:43.385Z","count":0,"uniques":0},{"timestamp":"2025-01-18T18:54:43.385Z","count":0,"uniques":0},{"timestamp":"2025-01-19T18:54:43.385Z","count":0,"uniques":0},{"timestamp":"2025-01-20T18:54:43.385Z","count":0,"uniques":0},{"timestamp":"2025-01-21T18:54:43.385Z","count":0,"uniques":0},{"timestamp":"2025-01-22T18:54:43.385Z","count":0,"uniques":0},{"timestamp":"2025-01-23T18:54:43.385Z","count":0,"uniques":0},{"timestamp":"2025-01-24T18:54:43.385Z","count":0,"uniques":0},{"timestamp":"2025-01-25T18:54:43.385Z","count":0,"uniques":0},{"timestamp":"2025-01-26T18:54:43.385Z","count":0,"uniques":0},{"timestamp":"2025-01-27T18:54:43.385Z","count":0,"uniques":0},{"timestamp":"2025-01-28T18:54:43.385Z","count":0,"uniques":0},{"timestamp":"2025-01-29T18:54:43.385Z","count":0,"uniques":0},{"timestamp":"2025-01-30T18:54:43.385Z","count":0,"uniques":0},{"timestamp":"2025-01-31T18:54:43.385Z","count":0,"uniques":0},{"timestamp":"2025-02-01T18:54:43.385Z","count":0,"uniques":0},{"timestamp":"2025-02-02T18:54:43.385Z","count":0,"uniques":0},{"timestamp":"2025-02-03T18:54:43.385Z","count":0,"uniques":0},{"timestamp":"2025-02-04T18:54:43.385Z","count":0,"uniques":0},{"timestamp":"2025-02-05T18:54:43.385Z","count":0,"uniques":0},{"timestamp":"2025-02-06T18:54:43.385Z","count":0,"uniques":0},{"timestamp":"2025-02-07T18:54:43.385Z","count":0,"uniques":0},{"timestamp":"2025-02-08T18:54:43.385Z","count":0,"uniques":0},{"timestamp":"2025-02-09T18:54:43.385Z","count":0,"uniques":0},{"timestamp":"2025-02-10T18:54:43.385Z","count":0,"uniques":0},{"timestamp":"2025-02-11T18:54:43.385Z","count":0,"uniques":0},{"timestamp":"2025-02-12T18:54:43.385Z","count":0,"uniques":0},{"timestamp":"2025-02-13T18:54:43.385Z","count":0,"uniques":0},{"timestamp":"2025-02-14T18:54:43.385Z","count":0,"uniques":0},{"timestamp":"2025-02-15T18:54:43.385Z","count":0,"uniques":0},{"timestamp":"2025-02-16T18:54:43.385Z","count":0,"uniques":0},{"timestamp":"2025-02-17T18:54:43.385Z","count":0,"uniques":0},{"timestamp":"2025-02-18T18:54:43.385Z","count":0,"uniques":0},{"timestamp":"2025-02-19T18:54:43.385Z","count":0,"uniques":0},{"timestamp":"2025-02-20T18:54:43.385Z","count":0,"uniques":0},{"timestamp":"2025-02-21T18:54:43.385Z","count":0,"uniques":0},{"timestamp":"2025-02-22T18:54:43.385Z","count":0,"uniques":0},{"timestamp":"2025-02-23T18:54:43.385Z","count":0,"uniques":0},{"timestamp":"2025-02-24T18:54:43.385Z","count":0,"uniques":0},{"timestamp":"2025-02-25T18:54:43.385Z","count":0,"uniques":0},{"timestamp":"2025-02-26T18:54:43.385Z","count":0,"uniques":0},{"timestamp":"2025-02-27T18:54:43.385Z","count":0,"uniques":0},{"timestamp":"2025-02-28T18:54:43.385Z","count":0,"uniques":0},{"timestamp":"2025-03-01T18:54:43.385Z","count":0,"uniques":0},{"timestamp":"2025-03-02T18:54:43.385Z","count":0,"uniques":0},{"timestamp":"2025-03-03T18:54:43.385Z","count":0,"uniques":0},{"timestamp":"2025-03-04T18:54:43.385Z","count":0,"uniques":0},{"timestamp":"2025-03-05T00:58:06.780Z","count":0,"uniques":0},{"timestamp":"2025-03-06T00:58:37.007Z","count":0,"uniques":0},{"timestamp":"2025-03-07T00:59:29.421Z","count":0,"uniques":0},{"timestamp":"2025-03-08T00:45:59.338Z","count":0,"uniques":0},{"timestamp":"2025-03-09T00:00:00.000Z","count":1,"uniques":1},{"timestamp":"2025-03-10T00:49:01.418Z","count":0,"uniques":0},{"timestamp":"2025-03-11T00:00:00.000Z","count":1,"uniques":1},{"timestamp":"2025-03-12T00:00:00.000Z","count":1,"uniques":1},{"timestamp":"2025-03-13T00:58:46.249Z","count":0,"uniques":0},{"timestamp":"2025-03-14T00:58:09.357Z","count":0,"uniques":0},{"timestamp":"2025-03-15T00:57:33.566Z","count":0,"uniques":0},{"timestamp":"2025-03-16T01:02:49.884Z","count":0,"uniques":0},{"timestamp":"2025-03-17T01:00:35.284Z","count":0,"uniques":0},{"timestamp":"2025-03-18T00:58:43.635Z","count":0,"uniques":0},{"timestamp":"2025-03-19T00:59:14.520Z","count":0,"uniques":0},{"timestamp":"2025-03-20T00:58:24.685Z","count":0,"uniques":0},{"timestamp":"2025-03-21T01:00:07.693Z","count":0,"uniques":0},{"timestamp":"2025-03-22T00:57:49.473Z","count":0,"uniques":0},{"timestamp":"2025-03-23T00:00:00.000Z","count":1,"uniques":1},{"timestamp":"2025-03-24T01:01:38.038Z","count":0,"uniques":0},{"timestamp":"2025-03-25T00:00:00.000Z","count":2,"uniques":1},{"timestamp":"2025-03-26T00:00:00.000Z","count":10,"uniques":1},{"timestamp":"2025-03-27T00:59:58.943Z","count":0,"uniques":0},{"timestamp":"2025-03-28T00:59:19.655Z","count":0,"uniques":0},{"timestamp":"2025-03-29T00:59:21.717Z","count":0,"uniques":0},{"timestamp":"2025-03-30T01:04:21.669Z","count":0,"uniques":0},{"timestamp":"2025-03-31T01:03:07.256Z","count":0,"uniques":0},{"timestamp":"2025-04-01T01:07:44.419Z","count":0,"uniques":0},{"timestamp":"2025-04-02T01:00:45.703Z","count":0,"uniques":0},{"timestamp":"2025-04-03T00:59:53.218Z","count":0,"uniques":0},{"timestamp":"2025-04-04T00:59:49.175Z","count":0,"uniques":0},{"timestamp":"2025-04-05T00:59:00.179Z","count":0,"uniques":0},{"timestamp":"2025-04-06T00:00:00.000Z","count":1,"uniques":1},{"timestamp":"2025-04-07T00:00:00.000Z","count":3,"uniques":1},{"timestamp":"2025-04-08T01:00:10.323Z","count":0,"uniques":0},{"timestamp":"2025-04-09T01:00:29.414Z","count":0,"uniques":0},{"timestamp":"2025-04-10T01:00:26.205Z","count":0,"uniques":0},{"timestamp":"2025-04-11T01:01:29.098Z","count":0,"uniques":0},{"timestamp":"2025-04-12T01:00:03.089Z","count":0,"uniques":0},{"timestamp":"2025-04-13T02:30:03.097Z","count":0,"uniques":0},{"timestamp":"2025-04-14T01:03:59.974Z","count":0,"uniques":0},{"timestamp":"2025-04-15T01:02:22.586Z","count":0,"uniques":0},{"timestamp":"2025-04-16T12:46:04.467Z","count":0,"uniques":0},{"timestamp":"2025-04-17T12:46:04.467Z","count":0,"uniques":0},{"timestamp":"2025-04-18T12:46:04.467Z","count":0,"uniques":0},{"timestamp":"2025-04-19T12:46:04.467Z","count":0,"uniques":0},{"timestamp":"2025-04-20T12:46:04.467Z","count":0,"uniques":0},{"timestamp":"2025-04-21T12:46:04.467Z","count":0,"uniques":0},{"timestamp":"2025-04-22T12:46:04.467Z","count":0,"uniques":0},{"timestamp":"2025-04-23T12:46:04.467Z","count":0,"uniques":0},{"timestamp":"2025-04-24T12:46:04.467Z","count":0,"uniques":0},{"timestamp":"2025-04-25T12:46:04.467Z","count":0,"uniques":0},{"timestamp":"2025-04-26T12:46:04.467Z","count":0,"uniques":0},{"timestamp":"2025-04-27T12:46:04.467Z","count":0,"uniques":0},{"timestamp":"2025-04-28T12:46:04.467Z","count":0,"uniques":0},{"timestamp":"2025-04-29T12:46:04.467Z","count":0,"uniques":0},{"timestamp":"2025-04-30T01:02:51.159Z","count":0,"uniques":0},{"timestamp":"2025-05-01T01:08:27.811Z","count":0,"uniques":0},{"timestamp":"2025-05-02T01:02:30.650Z","count":0,"uniques":0},{"timestamp":"2025-05-03T01:01:03.549Z","count":0,"uniques":0},{"timestamp":"2025-05-04T01:08:04.075Z","count":0,"uniques":0},{"timestamp":"2025-05-05T01:05:24.150Z","count":0,"uniques":0},{"timestamp":"2025-05-06T01:03:26.818Z","count":0,"uniques":0},{"timestamp":"2025-05-07T01:03:42.350Z","count":0,"uniques":0},{"timestamp":"2025-05-08T01:03:35.450Z","count":0,"uniques":0},{"timestamp":"2025-05-09T00:00:00.000Z","count":1,"uniques":1},{"timestamp":"2025-05-10T01:01:13.729Z","count":0,"uniques":0},{"timestamp":"2025-05-11T01:07:41.188Z","count":0,"uniques":0},{"timestamp":"2025-05-12T01:05:39.363Z","count":0,"uniques":0},{"timestamp":"2025-05-13T01:03:45.344Z","count":0,"uniques":0},{"timestamp":"2025-05-14T01:03:35.664Z","count":0,"uniques":0},{"timestamp":"2025-05-15T01:01:54.547Z","count":0,"uniques":0},{"timestamp":"2025-05-16T01:04:27.584Z","count":0,"uniques":0},{"timestamp":"2025-05-17T01:02:35.705Z","count":0,"uniques":0},{"timestamp":"2025-05-18T01:07:54.504Z","count":0,"uniques":0},{"timestamp":"2025-05-19T01:07:01.366Z","count":0,"uniques":0},{"timestamp":"2025-05-20T01:04:46.419Z","count":0,"uniques":0},{"timestamp":"2025-05-21T01:04:44.767Z","count":0,"uniques":0},{"timestamp":"2025-05-22T01:03:52.021Z","count":0,"uniques":0},{"timestamp":"2025-05-23T00:00:00.000Z","count":3,"uniques":1},{"timestamp":"2025-05-24T01:01:27.117Z","count":0,"uniques":0},{"timestamp":"2025-05-25T01:09:21.633Z","count":0,"uniques":0},{"timestamp":"2025-05-26T01:06:02.319Z","count":0,"uniques":0},{"timestamp":"2025-05-27T01:02:52.676Z","count":0,"uniques":0},{"timestamp":"2025-05-28T01:04:42.986Z","count":0,"uniques":0},{"timestamp":"2025-05-29T01:04:21.714Z","count":0,"uniques":0},{"timestamp":"2025-05-30T01:03:28.268Z","count":0,"uniques":0},{"timestamp":"2025-05-31T01:03:18.611Z","count":0,"uniques":0},{"timestamp":"2025-06-01T01:16:35.215Z","count":0,"uniques":0},{"timestamp":"2025-06-02T01:07:20.672Z","count":0,"uniques":0},{"timestamp":"2025-06-03T01:05:20.943Z","count":0,"uniques":0},{"timestamp":"2025-06-04T01:05:11.150Z","count":0,"uniques":0},{"timestamp":"2025-06-05T01:04:18.381Z","count":0,"uniques":0},{"timestamp":"2025-06-06T01:04:31.440Z","count":0,"uniques":0},{"timestamp":"2025-06-07T01:03:58.647Z","count":0,"uniques":0},{"timestamp":"2025-06-08T01:10:49.446Z","count":0,"uniques":0},{"timestamp":"2025-06-09T01:08:52.063Z","count":0,"uniques":0},{"timestamp":"2025-06-10T01:05:45.020Z","count":0,"uniques":0},{"timestamp":"2025-06-11T01:05:27.624Z","count":0,"uniques":0},{"timestamp":"2025-06-12T01:04:45.185Z","count":0,"uniques":0},{"timestamp":"2025-06-13T01:06:01.181Z","count":0,"uniques":0},{"timestamp":"2025-06-14T01:03:41.427Z","count":0,"uniques":0},{"timestamp":"2025-06-15T01:11:54.017Z","count":0,"uniques":0},{"timestamp":"2025-06-16T01:07:36.143Z","count":0,"uniques":0},{"timestamp":"2025-06-17T01:05:56.883Z","count":0,"uniques":0},{"timestamp":"2025-06-18T01:05:15.022Z","count":0,"uniques":0},{"timestamp":"2025-06-19T01:06:02.593Z","count":0,"uniques":0},{"timestamp":"2025-06-20T01:05:14.566Z","count":0,"uniques":0},{"timestamp":"2025-06-21T01:04:18.912Z","count":0,"uniques":0},{"timestamp":"2025-06-22T01:11:52.429Z","count":0,"uniques":0},{"timestamp":"2025-06-23T01:09:53.264Z","count":0,"uniques":0},{"timestamp":"2025-06-24T01:06:17.876Z","count":0,"uniques":0},{"timestamp":"2025-06-25T01:06:29.992Z","count":0,"uniques":0},{"timestamp":"2025-06-26T01:06:01.880Z","count":0,"uniques":0},{"timestamp":"2025-06-27T01:06:15.574Z","count":0,"uniques":0},{"timestamp":"2025-06-28T01:04:30.575Z","count":0,"uniques":0},{"timestamp":"2025-06-29T01:12:58.511Z","count":0,"uniques":0},{"timestamp":"2025-06-30T01:10:11.698Z","count":0,"uniques":0},{"timestamp":"2025-07-01T01:13:02.721Z","count":0,"uniques":0},{"timestamp":"2025-07-02T01:06:30.083Z","count":0,"uniques":0},{"timestamp":"2025-07-03T01:05:56.630Z","count":0,"uniques":0},{"timestamp":"2025-07-04T01:05:31.823Z","count":0,"uniques":0},{"timestamp":"2025-07-05T01:03:43.288Z","count":0,"uniques":0},{"timestamp":"2025-07-06T01:11:59.145Z","count":0,"uniques":0},{"timestamp":"2025-07-07T01:10:55.442Z","count":0,"uniques":0},{"timestamp":"2025-07-08T01:06:54.106Z","count":0,"uniques":0},{"timestamp":"2025-07-09T01:07:15.564Z","count":0,"uniques":0},{"timestamp":"2025-07-10T00:00:00.000Z","count":1,"uniques":1},{"timestamp":"2025-07-11T01:07:48.865Z","count":0,"uniques":0},{"timestamp":"2025-07-12T01:09:35.957Z","count":0,"uniques":0},{"timestamp":"2025-07-13T01:14:38.653Z","count":0,"uniques":0},{"timestamp":"2025-07-14T01:11:04.365Z","count":0,"uniques":0},{"timestamp":"2025-07-15T01:10:25.724Z","count":0,"uniques":0},{"timestamp":"2025-07-16T01:09:34.310Z","count":0,"uniques":0},{"timestamp":"2025-07-17T01:09:17.315Z","count":0,"uniques":0},{"timestamp":"2025-07-18T00:00:00.000Z","count":6,"uniques":1},{"timestamp":"2025-07-19T01:07:39.225Z","count":0,"uniques":0},{"timestamp":"2025-07-20T01:15:37.780Z","count":0,"uniques":0},{"timestamp":"2025-07-21T01:13:06.320Z","count":0,"uniques":0},{"timestamp":"2025-07-22T01:09:43.028Z","count":0,"uniques":0},{"timestamp":"2025-07-23T01:10:24.371Z","count":0,"uniques":0},{"timestamp":"2025-07-24T01:09:34.868Z","count":0,"uniques":0},{"timestamp":"2025-07-25T01:09:33.562Z","count":0,"uniques":0},{"timestamp":"2025-07-26T01:07:49.775Z","count":0,"uniques":0},{"timestamp":"2025-07-27T01:16:19.308Z","count":0,"uniques":0},{"timestamp":"2025-07-28T01:14:02.554Z","count":0,"uniques":0},{"timestamp":"2025-07-29T06:24:37.825Z","count":0,"uniques":0},{"timestamp":"2025-07-30T01:10:36.477Z","count":0,"uniques":0},{"timestamp":"2025-07-31T01:10:34.028Z","count":0,"uniques":0},{"timestamp":"2025-08-01T01:18:18.399Z","count":0,"uniques":0},{"timestamp":"2025-08-02T01:07:49.540Z","count":0,"uniques":0},{"timestamp":"2025-08-03T01:17:17.945Z","count":0,"uniques":0},{"timestamp":"2025-08-04T01:15:50.833Z","count":0,"uniques":0},{"timestamp":"2025-08-05T01:12:50.283Z","count":0,"uniques":0},{"timestamp":"2025-08-06T01:11:02.018Z","count":0,"uniques":0},{"timestamp":"2025-08-07T01:12:06.293Z","count":0,"uniques":0},{"timestamp":"2025-08-08T01:11:07.437Z","count":0,"uniques":0},{"timestamp":"2025-08-09T01:05:12.006Z","count":0,"uniques":0},{"timestamp":"2025-08-10T01:14:38.287Z","count":0,"uniques":0},{"timestamp":"2025-08-11T01:12:07.478Z","count":0,"uniques":0},{"timestamp":"2025-08-12T01:05:18.661Z","count":0,"uniques":0},{"timestamp":"2025-08-13T01:06:34.397Z","count":0,"uniques":0},{"timestamp":"2025-08-14T01:07:13.371Z","count":0,"uniques":0},{"timestamp":"2025-08-15T01:07:08.021Z","count":0,"uniques":0},{"timestamp":"2025-08-16T01:04:05.569Z","count":0,"uniques":0},{"timestamp":"2025-08-17T01:11:20.751Z","count":0,"uniques":0},{"timestamp":"2025-08-18T01:10:25.391Z","count":0,"uniques":0},{"timestamp":"2025-08-19T01:04:02.604Z","count":0,"uniques":0},{"timestamp":"2025-08-20T01:02:08.717Z","count":0,"uniques":0},{"timestamp":"2025-08-21T01:01:04.594Z","count":0,"uniques":0},{"timestamp":"2025-08-22T01:02:41.230Z","count":0,"uniques":0},{"timestamp":"2025-08-23T01:00:03.098Z","count":0,"uniques":0},{"timestamp":"2025-08-24T01:08:44.488Z","count":0,"uniques":0},{"timestamp":"2025-08-25T00:00:00.000Z","count":1,"uniques":1},{"timestamp":"2025-08-26T01:03:07.751Z","count":0,"uniques":0},{"timestamp":"2025-08-27T01:02:13.588Z","count":0,"uniques":0},{"timestamp":"2025-08-28T01:00:37.086Z","count":0,"uniques":0},{"timestamp":"2025-08-29T01:00:42.638Z","count":0,"uniques":0},{"timestamp":"2025-08-30T00:58:04.876Z","count":0,"uniques":0},{"timestamp":"2025-08-31T01:05:12.774Z","count":0,"uniques":0},{"timestamp":"2025-09-01T01:11:18.706Z","count":0,"uniques":0},{"timestamp":"2025-09-02T01:02:02.072Z","count":0,"uniques":0},{"timestamp":"2025-09-03T00:57:56.557Z","count":0,"uniques":0},{"timestamp":"2025-09-04T00:58:23.752Z","count":0,"uniques":0},{"timestamp":"2025-09-05T00:59:51.290Z","count":0,"uniques":0},{"timestamp":"2025-09-06T00:58:10.382Z","count":0,"uniques":0},{"timestamp":"2025-09-07T01:04:16.913Z","count":0,"uniques":0},{"timestamp":"2025-09-08T01:03:06.618Z","count":0,"uniques":0},{"timestamp":"2025-09-09T01:00:27.667Z","count":0,"uniques":0},{"timestamp":"2025-09-10T00:58:53.831Z","count":0,"uniques":0},{"timestamp":"2025-09-11T00:59:51.198Z","count":0,"uniques":0},{"timestamp":"2025-09-12T00:57:57.331Z","count":0,"uniques":0},{"timestamp":"2025-09-13T00:55:56.917Z","count":0,"uniques":0},{"timestamp":"2025-09-14T01:03:48.461Z","count":0,"uniques":0},{"timestamp":"2025-09-15T01:03:50.560Z","count":0,"uniques":0},{"timestamp":"2025-09-16T00:58:57.758Z","count":0,"uniques":0},{"timestamp":"2025-09-17T00:58:38.037Z","count":0,"uniques":0},{"timestamp":"2025-09-18T00:58:33.253Z","count":0,"uniques":0},{"timestamp":"2025-09-19T01:00:55.949Z","count":0,"uniques":0},{"timestamp":"2025-09-20T00:57:54.947Z","count":0,"uniques":0},{"timestamp":"2025-09-21T01:05:08.895Z","count":0,"uniques":0},{"timestamp":"2025-09-22T01:04:39.867Z","count":0,"uniques":0},{"timestamp":"2025-09-23T00:58:51.286Z","count":0,"uniques":0},{"timestamp":"2025-09-24T00:59:38.041Z","count":0,"uniques":0},{"timestamp":"2025-09-25T01:01:10.315Z","count":0,"uniques":0},{"timestamp":"2025-09-26T00:59:30.197Z","count":0,"uniques":0},{"timestamp":"2025-09-27T00:57:05.273Z","count":0,"uniques":0},{"timestamp":"2025-09-28T01:05:57.260Z","count":0,"uniques":0},{"timestamp":"2025-09-29T01:01:19.658Z","count":0,"uniques":0},{"timestamp":"2025-09-30T01:00:17.406Z","count":0,"uniques":0},{"timestamp":"2025-10-01T01:06:48.894Z","count":0,"uniques":0},{"timestamp":"2025-10-02T00:59:05.981Z","count":0,"uniques":0},{"timestamp":"2025-10-03T00:58:48.079Z","count":0,"uniques":0},{"timestamp":"2025-10-04T00:56:00.755Z","count":0,"uniques":0},{"timestamp":"2025-10-05T01:04:46.039Z","count":0,"uniques":0},{"timestamp":"2025-10-06T01:00:39.125Z","count":0,"uniques":0},{"timestamp":"2025-10-07T00:59:32.555Z","count":0,"uniques":0},{"timestamp":"2025-10-08T00:59:11.699Z","count":0,"uniques":0},{"timestamp":"2025-10-09T01:00:17.531Z","count":0,"uniques":0},{"timestamp":"2025-10-10T00:59:47.221Z","count":0,"uniques":0},{"timestamp":"2025-10-11T00:57:28.993Z","count":0,"uniques":0},{"timestamp":"2025-10-12T01:02:30.956Z","count":0,"uniques":0},{"timestamp":"2025-10-13T01:03:52.990Z","count":0,"uniques":0},{"timestamp":"2025-10-14T00:59:35.864Z","count":0,"uniques":0},{"timestamp":"2025-10-15T01:01:26.249Z","count":0,"uniques":0},{"timestamp":"2025-10-16T01:00:56.804Z","count":0,"uniques":0},{"timestamp":"2025-10-17T01:00:29.512Z","count":0,"uniques":0},{"timestamp":"2025-10-18T00:00:00.000Z","count":1,"uniques":1},{"timestamp":"2025-10-19T01:07:14.397Z","count":0,"uniques":0},{"timestamp":"2025-10-20T01:05:23.029Z","count":0,"uniques":0},{"timestamp":"2025-10-21T01:02:24.772Z","count":0,"uniques":0},{"timestamp":"2025-10-22T01:03:16.346Z","count":0,"uniques":0},{"timestamp":"2025-10-23T01:01:57.088Z","count":0,"uniques":0},{"timestamp":"2025-10-24T00:58:26.420Z","count":0,"uniques":0},{"timestamp":"2025-10-25T01:00:09.170Z","count":0,"uniques":0},{"timestamp":"2025-10-26T01:05:24.690Z","count":0,"uniques":0},{"timestamp":"2025-10-27T01:06:57.994Z","count":0,"uniques":0},{"timestamp":"2025-10-28T01:00:57.029Z","count":0,"uniques":0},{"timestamp":"2025-10-29T01:05:12.371Z","count":0,"uniques":0},{"timestamp":"2025-10-30T01:04:56.527Z","count":0,"uniques":0},{"timestamp":"2025-10-31T01:02:58.134Z","count":0,"uniques":0},{"timestamp":"2025-11-01T01:06:08.827Z","count":0,"uniques":0},{"timestamp":"2025-11-02T01:06:32.772Z","count":0,"uniques":0},{"timestamp":"2025-11-03T01:05:58.206Z","count":0,"uniques":0},{"timestamp":"2025-11-04T01:03:13.256Z","count":0,"uniques":0},{"timestamp":"2025-11-05T01:04:44.541Z","count":0,"uniques":0},{"timestamp":"2025-11-06T01:03:57.107Z","count":0,"uniques":0},{"timestamp":"2025-11-07T01:03:27.020Z","count":0,"uniques":0},{"timestamp":"2025-11-08T01:00:18.107Z","count":0,"uniques":0},{"timestamp":"2025-11-09T01:06:48.820Z","count":0,"uniques":0},{"timestamp":"2025-11-10T01:06:32.396Z","count":0,"uniques":0},{"timestamp":"2025-11-11T01:04:33.393Z","count":0,"uniques":0},{"timestamp":"2025-11-12T01:04:43.918Z","count":0,"uniques":0},{"timestamp":"2025-11-13T01:04:33.423Z","count":0,"uniques":0},{"timestamp":"2025-11-14T01:04:03.057Z","count":0,"uniques":0},{"timestamp":"2025-11-15T01:02:47.682Z","count":0,"uniques":0},{"timestamp":"2025-11-16T01:08:17.643Z","count":0,"uniques":0},{"timestamp":"2025-11-17T01:05:22.241Z","count":0,"uniques":0},{"timestamp":"2025-11-18T01:03:27.956Z","count":0,"uniques":0},{"timestamp":"2025-11-19T01:03:51.122Z","count":0,"uniques":0},{"timestamp":"2025-11-20T01:02:42.058Z","count":0,"uniques":0},{"timestamp":"2025-11-21T01:02:48.095Z","count":0,"uniques":0},{"timestamp":"2025-11-22T01:02:56.867Z","count":0,"uniques":0},{"timestamp":"2025-11-23T01:12:10.287Z","count":0,"uniques":0},{"timestamp":"2025-11-24T01:07:56.084Z","count":0,"uniques":0},{"timestamp":"2025-11-25T01:03:52.887Z","count":0,"uniques":0},{"timestamp":"2025-11-26T01:04:23.089Z","count":0,"uniques":0},{"timestamp":"2025-11-27T01:03:01.929Z","count":0,"uniques":0},{"timestamp":"2025-11-28T01:02:06.534Z","count":0,"uniques":0},{"timestamp":"2025-11-29T01:02:46.220Z","count":0,"uniques":0},{"timestamp":"2025-11-30T01:11:40.768Z","count":0,"uniques":0},{"timestamp":"2025-12-01T01:16:19.582Z","count":0,"uniques":0},{"timestamp":"2025-12-02T01:05:41.387Z","count":0,"uniques":0},{"timestamp":"2025-12-03T01:05:41.525Z","count":0,"uniques":0},{"timestamp":"2025-12-04T01:05:38.093Z","count":0,"uniques":0}]
